functions/__init__.py
functions/report.py
Report_of_Monaco_Second-0.0.6.dist-info/LICENSE
Report_of_Monaco_Second-0.0.6.dist-info/METADATA
Report_of_Monaco_Second-0.0.6.dist-info/WHEEL
Report_of_Monaco_Second-0.0.6.dist-info/top_level.txt
Report_of_Monaco_Second-0.0.6.dist-info/RECORD
